profile_viewer/__init__.py
profile_viewer/_meliaejson.py
profile_viewer/coldshotadapter.py
profile_viewer/homedirectory.py
profile_viewer/listviews.py
profile_viewer/macshim.py
profile_viewer/meliaeadapter.py
profile_viewer/meliaeloader.py
profile_viewer/pstatsadapter.py
profile_viewer/pstatsloader.py
profile_viewer/runsnake.py
profile_viewer-0.1.5.dist-info/DESCRIPTION.rst
profile_viewer-0.1.5.dist-info/METADATA
profile_viewer-0.1.5.dist-info/RECORD
profile_viewer-0.1.5.dist-info/WHEEL
profile_viewer-0.1.5.dist-info/entry_points.txt
profile_viewer-0.1.5.dist-info/metadata.json
profile_viewer-0.1.5.dist-info/top_level.txt
