Metadata-Version: 2.0
Name: profile-viewer
Version: 0.1.5
Summary: GUI Viewer for Python profiling runs
Home-page: http://www.vrplumber.com/programming/profile_viewer/
Author: Mike C. Fletcher
Author-email: mcfletch@vrplumber.com
License: BSD
Download-URL: http://www.vrplumber.com/programming/profile_viewer/
Keywords: profile,gui,wxPython,squaremap
Platform: Any
Classifier: License :: OSI Approved :: BSD License
Classifier: Programming Language :: Python
Classifier: Topic :: Software Development :: Libraries :: Python Modules
Classifier: Intended Audience :: Developers
Requires-Dist: SquareMap3 (>=1.0.3)
Requires-Dist: wxPython
